ptkcmd/__init__.py
ptkcmd/ptkcmd.py
ptkcmd-0.1.3.dist-info/LICENSE
ptkcmd-0.1.3.dist-info/METADATA
ptkcmd-0.1.3.dist-info/WHEEL
ptkcmd-0.1.3.dist-info/top_level.txt
ptkcmd-0.1.3.dist-info/RECORD
